LICENSE
MANIFEST.in
README.rst
VERSION
requirements.txt
setup.py
sagemath/__init__.py
sagemath/check_version.py
sagemath.egg-info/PKG-INFO
sagemath.egg-info/SOURCES.txt
sagemath.egg-info/dependency_links.txt
sagemath.egg-info/requires.txt
sagemath.egg-info/top_level.txt