Metadata-Version: 1.1
Name: sagemath
Version: 1.3.0
Summary: A free open-source mathematics software system
Home-page: https://www.sagemath.org
Author: The Sage Development Team
Author-email: marc.masdeu@gmail.com
License: GPLv3+
Keywords: SageMath
Platform: UNKNOWN
Classifier: Development Status :: 5 - Production/Stable
Classifier: Intended Audience :: Science/Research
Classifier: Topic :: Scientific/Engineering :: Mathematics
Classifier: License :: OSI Approved :: GNU General Public License v3 or later (GPLv3+)
Classifier: Programming Language :: Python :: 3.8
